auditpol/__init__.py
auditpol/policy.py
auditpol/settings.py
auditpol/subcategories.py
auditpol/utils.py
tests/__init__.py
tests/test_policy.py
tests/test_settings.py
tests/test_subcategories.py
tests/test_utils.py
auditpol-1.1.0.dist-info/LICENSE
auditpol-1.1.0.dist-info/METADATA
auditpol-1.1.0.dist-info/WHEEL
auditpol-1.1.0.dist-info/top_level.txt
auditpol-1.1.0.dist-info/RECORD
