Metadata-Version: 2.1
Name: auditpol
Version: 1.1.0
Summary: Windows Audit Policy parser and emitter for Python
Home-page: https://github.com/LiamSennitt/auditpol
Author: Liam Sennitt
License: UNKNOWN
Platform: UNKNOWN
